bud/__init__.py
bud-0.3.2.dist-info/DESCRIPTION.rst
bud-0.3.2.dist-info/METADATA
bud-0.3.2.dist-info/RECORD
bud-0.3.2.dist-info/WHEEL
bud-0.3.2.dist-info/entry_points.txt
bud-0.3.2.dist-info/metadata.json
bud-0.3.2.dist-info/top_level.txt
