Metadata-Version: 2.0
Name: bud
Version: 0.3.2
Summary: bud runs stuff for you
Home-page: https://github.com/hoffmann/bud
Author: Peter Hoffmann
Author-email: ph@peter-hoffmann.com
License: BSD
Platform: UNKNOWN
Classifier: Programming Language :: Python
Requires-Dist: PyYaml
Requires-Dist: click
